README.rst
setup.py
shredder/__init__.py
shredder/shredder.py
shredder.egg-info/PKG-INFO
shredder.egg-info/SOURCES.txt
shredder.egg-info/dependency_links.txt
shredder.egg-info/not-zip-safe
shredder.egg-info/top_level.txt