Metadata-Version: 1.1
Name: shredder
Version: 0.6
Summary: Simple multiprocessing
Home-page: http://github.com/svrana/shredder
Author: Shaw Vrana
Author-email: shaw@vranix.com
License: MIT
Platform: UNKNOWN
Classifier: License :: OSI Approved :: MIT License
